{
    "championships": 0,
    "code": null,
    "collection_name": "Paolo Barilla 🇮🇹",
    "country": "Italy",
    "country_code": "it",
    "country_flag": "🇮🇹",
    "did_not_finish": 5,
    "did_not_start": 6,
    "dob": "1961-04-20",
    "driverId": 147,
    "driverRef": "barilla",
    "fastestlaps": 0,
    "finished_in_points": 0,
    "first_race": "1989-10-22",
    "first_win": null,
    "forename": "Paolo",
    "fullname": "Paolo Barilla",
    "last_race": "1990-09-30",
    "last_win": null,
    "participations": 15,
    "permanent_number": null,
    "podiums": 0,
    "points": 0.0,
    "poles": 0,
    "races_finished": 4,
    "seasons": 2,
    "subchampionships": 0,
    "surname": "Barilla",
    "top_ten": 0,
    "wins": 0
}