{
    "championships": 0,
    "code": null,
    "collection_name": "Carlo Facetti 🇮🇹",
    "country": "Italy",
    "country_code": "it",
    "country_flag": "🇮🇹",
    "did_not_finish": 0,
    "did_not_start": 1,
    "dob": "1935-06-26",
    "driverId": 325,
    "driverRef": "facetti",
    "fastestlaps": 0,
    "finished_in_points": 0,
    "first_race": "1974-09-08",
    "first_win": null,
    "forename": "Carlo",
    "fullname": "Carlo Facetti",
    "last_race": "1974-09-08",
    "last_win": null,
    "participations": 1,
    "permanent_number": null,
    "podiums": 0,
    "points": 0.0,
    "poles": 0,
    "races_finished": 0,
    "seasons": 1,
    "subchampionships": 0,
    "surname": "Facetti",
    "top_ten": 0,
    "wins": 0
}