{
    "championships": 0,
    "code": null,
    "collection_name": "Tim Schenken 🇦🇺",
    "country": "Australia",
    "country_code": "au",
    "country_flag": "🇦🇺",
    "did_not_finish": 18,
    "did_not_start": 2,
    "dob": "1943-09-26",
    "driverId": 314,
    "driverRef": "schenken",
    "fastestlaps": 0,
    "finished_in_points": 3,
    "first_race": "1970-08-16",
    "first_win": null,
    "forename": "Tim",
    "fullname": "Tim Schenken",
    "last_race": "1974-10-06",
    "last_win": null,
    "participations": 36,
    "permanent_number": null,
    "podiums": 1,
    "points": 7.0,
    "poles": 0,
    "races_finished": 16,
    "seasons": 5,
    "subchampionships": 0,
    "surname": "Schenken",
    "top_ten": 9,
    "wins": 0
}