[
    {
        "title": "List of All Formula 1速 Races at Brands Hatch",
        "url": "races"
    },
    {
        "title": "List of All Formula 1速 Drivers that Have Raced at Brands Hatch",
        "url": "all-drivers"
    },
    {
        "title": "List of All Formula 1速 Drivers that Have Won a Race at Brands Hatch",
        "url": "winning-drivers"
    },
    {
        "title": "List of All Formula 1速 Drivers that Have Been in the Podium at Brands Hatch",
        "url": "podium-drivers"
    }
]